odoo/addons/l10n_fr_cog/README.rst
odoo/addons/l10n_fr_cog/__init__.py
odoo/addons/l10n_fr_cog/__manifest__.py
odoo/addons/l10n_fr_cog/post_install.py
odoo/addons/l10n_fr_cog/data/res_country.xml
odoo/addons/l10n_fr_cog/i18n/es.po
odoo/addons/l10n_fr_cog/i18n/fr.po
odoo/addons/l10n_fr_cog/i18n/l10n_fr_cog.pot
odoo/addons/l10n_fr_cog/models/__init__.py
odoo/addons/l10n_fr_cog/models/res_country.py
odoo/addons/l10n_fr_cog/readme/CONTRIBUTORS.md
odoo/addons/l10n_fr_cog/readme/DESCRIPTION.md
odoo/addons/l10n_fr_cog/static/description/icon.png
odoo/addons/l10n_fr_cog/static/description/index.html
odoo/addons/l10n_fr_cog/views/res_country.xml
odoo_addon_l10n_fr_cog-18.0.1.0.0.3.dist-info/METADATA
odoo_addon_l10n_fr_cog-18.0.1.0.0.3.dist-info/WHEEL
odoo_addon_l10n_fr_cog-18.0.1.0.0.3.dist-info/top_level.txt
odoo_addon_l10n_fr_cog-18.0.1.0.0.3.dist-info/RECORD
